myCalculatorPackage333/__init__.py
myCalculatorPackage333/division/__init__.py
myCalculatorPackage333/division/divide.py
myCalculatorPackage333/multiplication/__init__.py
myCalculatorPackage333/multiplication/multiply.py
myCalculatorPackage333-0.0.2.dist-info/LICENSE.txt
myCalculatorPackage333-0.0.2.dist-info/METADATA
myCalculatorPackage333-0.0.2.dist-info/WHEEL
myCalculatorPackage333-0.0.2.dist-info/top_level.txt
myCalculatorPackage333-0.0.2.dist-info/RECORD
